pytest_fv/__build_num__.py
pytest_fv/__ext__.py
pytest_fv/__init__.py
pytest_fv/console.py
pytest_fv/dirconfig.py
pytest_fv/env.py
pytest_fv/env_action.py
pytest_fv/ext.py
pytest_fv/ext_rgy.py
pytest_fv/file_set.py
pytest_fv/fixtures.py
pytest_fv/flow.py
pytest_fv/flow_sim.py
pytest_fv/fs.py
pytest_fv/fs_config.py
pytest_fv/fs_paths.py
pytest_fv/fs_vlnv.py
pytest_fv/fusesoc.py
pytest_fv/fv_config.py
pytest_fv/hdl_sim.py
pytest_fv/hdl_sim_ext.py
pytest_fv/path_src.py
pytest_fv/phase.py
pytest_fv/phase_compound.py
pytest_fv/phase_pre_post.py
pytest_fv/project_info.py
pytest_fv/task.py
pytest_fv/task_cmd.py
pytest_fv/task_delegator.py
pytest_fv/task_flow.py
pytest_fv/task_group.py
pytest_fv/task_list.py
pytest_fv/test_case.py
pytest_fv/tool_rgy.py
pytest_fv/exts/hdl/sim/ext_cocotb.py
pytest_fv/exts/test/__init__.py
pytest_fv/exts/test/pss/__init__.py
pytest_fv/exts/test/pss/ext_pss.py
pytest_fv/exts/test/pss/ext_pss_zuspec.py
pytest_fv/impl/path_src_ivpm.py
pytest_fv/tasks/__init__.py
pytest_fv/tasks/task_create_file.py
pytest_fv/tool/__init__.py
pytest_fv/tool/hdl/__init__.py
pytest_fv/tool/hdl/sim/__init__.py
pytest_fv/tool/hdl/sim/sim_iverilog.py
pytest_fv/tool/hdl/sim/sim_mti.py
pytest_fv/tool/hdl/sim/sim_vcs.py
pytest_fv/tool/hdl/sim/sim_verilator.py
pytest_fv/tool/hdl/sim/sim_vlog_base.py
pytest_fv/tool/hdl/sim/sim_xcelium.py
pytest_fv/tool/hdl/sim/sim_xsim.py
pytest_fv-0.0.1.15479793400.dist-info/licenses/LICENSE
pytest_fv-0.0.1.15479793400.dist-info/METADATA
pytest_fv-0.0.1.15479793400.dist-info/WHEEL
pytest_fv-0.0.1.15479793400.dist-info/entry_points.txt
pytest_fv-0.0.1.15479793400.dist-info/top_level.txt
pytest_fv-0.0.1.15479793400.dist-info/RECORD
