Metadata-Version: 2.4
Name: pytest-fv
Version: 0.0.1.15479793400
Summary: pytest extensions to support running functional-verification jobs
Home-page: https://github.com/fvutils/pytest-fv
Author: Matthew Ballance
Author-email: matt.ballance@gmail.com
License: Apache 2.0
Keywords: SystemVerilog,Verilog,RTL,Coverage
License-File: LICENSE
Requires-Dist: fusesoc
Requires-Dist: pytest
Requires-Dist: svdep
Dynamic: author
Dynamic: author-email
Dynamic: description
Dynamic: home-page
Dynamic: keywords
Dynamic: license
Dynamic: license-file
Dynamic: requires-dist
Dynamic: summary
